{
  "metadata": {
    "generated": "2026-04-30",
    "source": "https://judicious-night-bca.notion.site/Illustrator-Reference-bb586c9667764361b2ed3aa312049d35",
    "lastUpdate": "2025-12-29",
    "targetVersion": "30.0.0",
    "menuCommandCount": 680,
    "selectToolCount": 100,
    "usefulForProject": [
      "ExtendScript app.executeMenuCommand command lookup",
      "ExtendScript app.selectTool tool-name lookup",
      "AppleScript/JXA examples for macOS automation only"
    ]
  },
  "tools": [
    {
      "index": 1,
      "id": "toolName_1",
      "toolName": "Adobe Type Tool",
      "category": "Type",
      "tool_en": "Type Tool",
      "tool_ja": "文字",
      "extendscript": "app.selectTool('Adobe Type Tool');",
      "applescript": "Select Tool tool name \"Adobe Type Tool\"",
      "jxa": "app.selectTool({toolName: 'Adobe Type Tool'});",
      "minVersion": "24"
    },
    {
      "index": 2,
      "id": "toolName_2",
      "toolName": "Adobe Area Type Tool",
      "category": "Type",
      "tool_en": "Area Type Tool",
      "tool_ja": "エリア内文字",
      "extendscript": "app.selectTool('Adobe Area Type Tool');",
      "applescript": "Select Tool tool name \"Adobe Area Type Tool\"",
      "jxa": "app.selectTool({toolName: 'Adobe Area Type Tool'});",
      "minVersion": "24"
    },
    {
      "index": 3,
      "id": "toolName_3",
      "toolName": "Adobe Path Type Tool",
      "category": "Type",
      "tool_en": "Type on a Path Tool",
      "tool_ja": "パス上文字",
      "extendscript": "app.selectTool('Adobe Path Type Tool');",
      "applescript": "Select Tool tool name \"Adobe Path Type Tool\"",
      "jxa": "app.selectTool({toolName: 'Adobe Path Type Tool'});",
      "minVersion": "24"
    },
    {
      "index": 4,
      "id": "toolName_4",
      "toolName": "Adobe Vertical Type Tool",
      "category": "Type",
      "tool_en": "Vertical Type Tool",
      "tool_ja": "文字 (縦)",
      "extendscript": "app.selectTool('Adobe Vertical Type Tool');",
      "applescript": "Select Tool tool name \"Adobe Vertical Type Tool\"",
      "jxa": "app.selectTool({toolName: 'Adobe Vertical Type Tool'});",
      "minVersion": "24"
    },
    {
      "index": 5,
      "id": "toolName_5",
      "toolName": "Adobe Vertical Area Type Tool",
      "category": "Type",
      "tool_en": "Vertical Area Type Tool",
      "tool_ja": "エリア内文字 (縦)",
      "extendscript": "app.selectTool('Adobe Vertical Area Type Tool');",
      "applescript": "Select Tool tool name \"Adobe Vertical Area Type Tool\"",
      "jxa": "app.selectTool({toolName: 'Adobe Vertical Area Type Tool'});",
      "minVersion": "24"
    },
    {
      "index": 6,
      "id": "toolName_6",
      "toolName": "Adobe Vertical Path Type Tool",
      "category": "Type",
      "tool_en": "Vertical Type on a Path Tool",
      "tool_ja": "パス上文字 (縦)",
      "extendscript": "app.selectTool('Adobe Vertical Path Type Tool');",
      "applescript": "Select Tool tool name \"Adobe Vertical Path Type Tool\"",
      "jxa": "app.selectTool({toolName: 'Adobe Vertical Path Type Tool'});",
      "minVersion": "24"
    },
    {
      "index": 7,
      "id": "toolName_7",
      "toolName": "Adobe Touch Type Tool",
      "category": "Type",
      "tool_en": "Touch Type Tool",
      "tool_ja": "文字タッチ",
      "extendscript": "app.selectTool('Adobe Touch Type Tool');",
      "applescript": "Select Tool tool name \"Adobe Touch Type Tool\"",
      "jxa": "app.selectTool({toolName: 'Adobe Touch Type Tool'});",
      "minVersion": "24"
    },
    {
      "index": 8,
      "id": "toolName_8",
      "toolName": "Adobe Right-To-Left Type Tool",
      "category": "Type",
      "tool_en": "",
      "tool_ja": "",
      "extendscript": "app.selectTool('Adobe Right-To-Left Type Tool');",
      "applescript": "Select Tool tool name \"Adobe Right-To-Left Type Tool\"",
      "jxa": "app.selectTool({toolName: 'Adobe Right-To-Left Type Tool'});",
      "minVersion": "24"
    },
    {
      "index": 9,
      "id": "toolName_9",
      "toolName": "Adobe Right-To-Left Area Type Tool",
      "category": "Type",
      "tool_en": "",
      "tool_ja": "",
      "extendscript": "app.selectTool('Adobe Right-To-Left Area Type Tool');",
      "applescript": "Select Tool tool name \"Adobe Right-To-Left Area Type Tool\"",
      "jxa": "app.selectTool({toolName: 'Adobe Right-To-Left Area Type Tool'});",
      "minVersion": "24"
    },
    {
      "index": 10,
      "id": "toolName_10",
      "toolName": "Adobe Right-To-Left Path Type Tool",
      "category": "Type",
      "tool_en": "",
      "tool_ja": "",
      "extendscript": "app.selectTool('Adobe Right-To-Left Path Type Tool');",
      "applescript": "Select Tool tool name \"Adobe Right-To-Left Path Type Tool\"",
      "jxa": "app.selectTool({toolName: 'Adobe Right-To-Left Path Type Tool'});",
      "minVersion": "24"
    },
    {
      "index": 11,
      "id": "toolName_11",
      "toolName": "Adobe Rounded Rectangle Tool",
      "category": "Draw 04",
      "tool_en": "Rounded Rectangle Tool",
      "tool_ja": "角丸長方形",
      "extendscript": "app.selectTool('Adobe Rounded Rectangle Tool');",
      "applescript": "Select Tool tool name \"Adobe Rounded Rectangle Tool\"",
      "jxa": "app.selectTool({toolName: 'Adobe Rounded Rectangle Tool'});",
      "minVersion": "24"
    },
    {
      "index": 12,
      "id": "toolName_12",
      "toolName": "Adobe Select Tool",
      "category": "Select 01",
      "tool_en": "Selection Tool",
      "tool_ja": "選択",
      "extendscript": "app.selectTool('Adobe Select Tool');",
      "applescript": "Select Tool tool name \"Adobe Select Tool\"",
      "jxa": "app.selectTool({toolName: 'Adobe Select Tool'});",
      "minVersion": "24"
    },
    {
      "index": 13,
      "id": "toolName_13",
      "toolName": "Adobe Direct Select Tool",
      "category": "Select 02",
      "tool_en": "Direct Selection Tool",
      "tool_ja": "ダイレクト選択",
      "extendscript": "app.selectTool('Adobe Direct Select Tool');",
      "applescript": "Select Tool tool name \"Adobe Direct Select Tool\"",
      "jxa": "app.selectTool({toolName: 'Adobe Direct Select Tool'});",
      "minVersion": "24"
    },
    {
      "index": 14,
      "id": "toolName_14",
      "toolName": "Adobe Direct Object Select Tool",
      "category": "Select 02",
      "tool_en": "Group Selection Tool",
      "tool_ja": "グループ選択",
      "extendscript": "app.selectTool('Adobe Direct Object Select Tool');",
      "applescript": "Select Tool tool name \"Adobe Direct Object Select Tool\"",
      "jxa": "app.selectTool({toolName: 'Adobe Direct Object Select Tool'});",
      "minVersion": "24"
    },
    {
      "index": 15,
      "id": "toolName_15",
      "toolName": "Adobe Scale Tool",
      "category": "Modify 02",
      "tool_en": "Scale Tool",
      "tool_ja": "拡大・縮小",
      "extendscript": "app.selectTool('Adobe Scale Tool');",
      "applescript": "Select Tool tool name \"Adobe Scale Tool\"",
      "jxa": "app.selectTool({toolName: 'Adobe Scale Tool'});",
      "minVersion": "24"
    },
    {
      "index": 16,
      "id": "toolName_16",
      "toolName": "Adobe Rotate Tool",
      "category": "Modify 01",
      "tool_en": "Rotate Tool",
      "tool_ja": "回転",
      "extendscript": "app.selectTool('Adobe Rotate Tool');",
      "applescript": "Select Tool tool name \"Adobe Rotate Tool\"",
      "jxa": "app.selectTool({toolName: 'Adobe Rotate Tool'});",
      "minVersion": "24"
    },
    {
      "index": 17,
      "id": "toolName_17",
      "toolName": "Adobe Reflect Tool",
      "category": "Modify 01",
      "tool_en": "Reflect Tool",
      "tool_ja": "リフレクト",
      "extendscript": "app.selectTool('Adobe Reflect Tool');",
      "applescript": "Select Tool tool name \"Adobe Reflect Tool\"",
      "jxa": "app.selectTool({toolName: 'Adobe Reflect Tool'});",
      "minVersion": "24"
    },
    {
      "index": 18,
      "id": "toolName_18",
      "toolName": "Adobe Shear Tool",
      "category": "Modify 02",
      "tool_en": "Shear Tool",
      "tool_ja": "シアー",
      "extendscript": "app.selectTool('Adobe Shear Tool');",
      "applescript": "Select Tool tool name \"Adobe Shear Tool\"",
      "jxa": "app.selectTool({toolName: 'Adobe Shear Tool'});",
      "minVersion": "24"
    },
    {
      "index": 19,
      "id": "toolName_19",
      "toolName": "Adobe Column Graph Tool",
      "category": "Draw 08",
      "tool_en": "Column Graph Tool",
      "tool_ja": "棒グラフ",
      "extendscript": "app.selectTool('Adobe Column Graph Tool');",
      "applescript": "Select Tool tool name \"Adobe Column Graph Tool\"",
      "jxa": "app.selectTool({toolName: 'Adobe Column Graph Tool'});",
      "minVersion": "24"
    },
    {
      "index": 20,
      "id": "toolName_20",
      "toolName": "Adobe Stacked Column Graph Tool",
      "category": "Draw 08",
      "tool_en": "Stacked Column Graph Tool",
      "tool_ja": "積み上げ棒グラフ",
      "extendscript": "app.selectTool('Adobe Stacked Column Graph Tool');",
      "applescript": "Select Tool tool name \"Adobe Stacked Column Graph Tool\"",
      "jxa": "app.selectTool({toolName: 'Adobe Stacked Column Graph Tool'});",
      "minVersion": "24"
    },
    {
      "index": 21,
      "id": "toolName_21",
      "toolName": "Adobe Line Graph Tool",
      "category": "Draw 08",
      "tool_en": "Line Graph Tool",
      "tool_ja": "折れ線グラフ",
      "extendscript": "app.selectTool('Adobe Line Graph Tool');",
      "applescript": "Select Tool tool name \"Adobe Line Graph Tool\"",
      "jxa": "app.selectTool({toolName: 'Adobe Line Graph Tool'});",
      "minVersion": "24"
    },
    {
      "index": 22,
      "id": "toolName_22",
      "toolName": "Adobe Pie Graph Tool",
      "category": "Draw 08",
      "tool_en": "Pie Graph Tool",
      "tool_ja": "円グラフ",
      "extendscript": "app.selectTool('Adobe Pie Graph Tool');",
      "applescript": "Select Tool tool name \"Adobe Pie Graph Tool\"",
      "jxa": "app.selectTool({toolName: 'Adobe Pie Graph Tool'});",
      "minVersion": "24"
    },
    {
      "index": 23,
      "id": "toolName_23",
      "toolName": "Adobe Area Graph Tool",
      "category": "Draw 08",
      "tool_en": "Area Graph Tool",
      "tool_ja": "階層グラフ",
      "extendscript": "app.selectTool('Adobe Area Graph Tool');",
      "applescript": "Select Tool tool name \"Adobe Area Graph Tool\"",
      "jxa": "app.selectTool({toolName: 'Adobe Area Graph Tool'});",
      "minVersion": "24"
    },
    {
      "index": 24,
      "id": "toolName_24",
      "toolName": "Adobe Scatter Graph Tool",
      "category": "Draw 08",
      "tool_en": "Scatter Graph Tool",
      "tool_ja": "散布図",
      "extendscript": "app.selectTool('Adobe Scatter Graph Tool');",
      "applescript": "Select Tool tool name \"Adobe Scatter Graph Tool\"",
      "jxa": "app.selectTool({toolName: 'Adobe Scatter Graph Tool'});",
      "minVersion": "24"
    },
    {
      "index": 25,
      "id": "toolName_25",
      "toolName": "Adobe Bar Graph Tool",
      "category": "Draw 08",
      "tool_en": "Bar Graph Tool",
      "tool_ja": "横向き棒グラフ",
      "extendscript": "app.selectTool('Adobe Bar Graph Tool');",
      "applescript": "Select Tool tool name \"Adobe Bar Graph Tool\"",
      "jxa": "app.selectTool({toolName: 'Adobe Bar Graph Tool'});",
      "minVersion": "24"
    },
    {
      "index": 26,
      "id": "toolName_26",
      "toolName": "Adobe Stacked Bar Graph Tool",
      "category": "Draw 08",
      "tool_en": "Stacked Bar Graph Tool",
      "tool_ja": "横向き積み上げ棒グラフ",
      "extendscript": "app.selectTool('Adobe Stacked Bar Graph Tool');",
      "applescript": "Select Tool tool name \"Adobe Stacked Bar Graph Tool\"",
      "jxa": "app.selectTool({toolName: 'Adobe Stacked Bar Graph Tool'});",
      "minVersion": "24"
    },
    {
      "index": 27,
      "id": "toolName_27",
      "toolName": "Adobe Radar Graph Tool",
      "category": "Draw 08",
      "tool_en": "Radar Graph Tool",
      "tool_ja": "レーダーチャート",
      "extendscript": "app.selectTool('Adobe Radar Graph Tool');",
      "applescript": "Select Tool tool name \"Adobe Radar Graph Tool\"",
      "jxa": "app.selectTool({toolName: 'Adobe Radar Graph Tool'});",
      "minVersion": "24"
    },
    {
      "index": 28,
      "id": "toolName_28",
      "toolName": "Adobe Scroll Tool",
      "category": "Navigate 01",
      "tool_en": "Hand Tool",
      "tool_ja": "手のひら",
      "extendscript": "app.selectTool('Adobe Scroll Tool');",
      "applescript": "Select Tool tool name \"Adobe Scroll Tool\"",
      "jxa": "app.selectTool({toolName: 'Adobe Scroll Tool'});",
      "minVersion": "24"
    },
    {
      "index": 29,
      "id": "toolName_29",
      "toolName": "Adobe Freehand Tool",
      "category": "Draw 06",
      "tool_en": "Pencil Tool",
      "tool_ja": "鉛筆",
      "extendscript": "app.selectTool('Adobe Freehand Tool');",
      "applescript": "Select Tool tool name \"Adobe Freehand Tool\"",
      "jxa": "app.selectTool({toolName: 'Adobe Freehand Tool'});",
      "minVersion": "24"
    },
    {
      "index": 30,
      "id": "toolName_30",
      "toolName": "Adobe Freehand Smooth Tool",
      "category": "Draw 06",
      "tool_en": "Smooth Tool",
      "tool_ja": "スムーズ",
      "extendscript": "app.selectTool('Adobe Freehand Smooth Tool');",
      "applescript": "Select Tool tool name \"Adobe Freehand Smooth Tool\"",
      "jxa": "app.selectTool({toolName: 'Adobe Freehand Smooth Tool'});",
      "minVersion": "24"
    },
    {
      "index": 31,
      "id": "toolName_31",
      "toolName": "Adobe Freehand Erase Tool",
      "category": "Draw 06",
      "tool_en": "Path Eraser Tool",
      "tool_ja": "パス消しゴム",
      "extendscript": "app.selectTool('Adobe Freehand Erase Tool');",
      "applescript": "Select Tool tool name \"Adobe Freehand Erase Tool\"",
      "jxa": "app.selectTool({toolName: 'Adobe Freehand Erase Tool'});",
      "minVersion": "24"
    },
    {
      "index": 32,
      "id": "toolName_32",
      "toolName": "Adobe Corner Join Tool",
      "category": "Draw 06",
      "tool_en": "Join Tool",
      "tool_ja": "連結ツール",
      "extendscript": "app.selectTool('Adobe Corner Join Tool');",
      "applescript": "Select Tool tool name \"Adobe Corner Join Tool\"",
      "jxa": "app.selectTool({toolName: 'Adobe Corner Join Tool'});",
      "minVersion": "24"
    },
    {
      "index": 33,
      "id": "toolName_33",
      "toolName": "Adobe Pen Tool",
      "category": "Draw 01",
      "tool_en": "Pen Tool",
      "tool_ja": "ペン",
      "extendscript": "app.selectTool('Adobe Pen Tool');",
      "applescript": "Select Tool tool name \"Adobe Pen Tool\"",
      "jxa": "app.selectTool({toolName: 'Adobe Pen Tool'});",
      "minVersion": "24"
    },
    {
      "index": 34,
      "id": "toolName_34",
      "toolName": "Adobe Blend Tool",
      "category": "Modify 06",
      "tool_en": "Blend Tool",
      "tool_ja": "ブレンド",
      "extendscript": "app.selectTool('Adobe Blend Tool');",
      "applescript": "Select Tool tool name \"Adobe Blend Tool\"",
      "jxa": "app.selectTool({toolName: 'Adobe Blend Tool'});",
      "minVersion": "24"
    },
    {
      "index": 35,
      "id": "toolName_35",
      "toolName": "Adobe Scissors Tool",
      "category": "Modify 07",
      "tool_en": "Scissors Tool",
      "tool_ja": "はさみ",
      "extendscript": "app.selectTool('Adobe Scissors Tool');",
      "applescript": "Select Tool tool name \"Adobe Scissors Tool\"",
      "jxa": "app.selectTool({toolName: 'Adobe Scissors Tool'});",
      "minVersion": "24"
    },
    {
      "index": 36,
      "id": "toolName_36",
      "toolName": "Adobe Measure Tool",
      "category": "Modify 05",
      "tool_en": "Measure Tool",
      "tool_ja": "ものさし",
      "extendscript": "app.selectTool('Adobe Measure Tool');",
      "applescript": "Select Tool tool name \"Adobe Measure Tool\"",
      "jxa": "app.selectTool({toolName: 'Adobe Measure Tool'});",
      "minVersion": "24"
    },
    {
      "index": 37,
      "id": "toolName_37",
      "toolName": "Adobe Page Tool",
      "category": "Navigate 01",
      "tool_en": "Print Tiling Tool",
      "tool_ja": "プリント分割",
      "extendscript": "app.selectTool('Adobe Page Tool');",
      "applescript": "Select Tool tool name \"Adobe Page Tool\"",
      "jxa": "app.selectTool({toolName: 'Adobe Page Tool'});",
      "minVersion": "24"
    },
    {
      "index": 38,
      "id": "toolName_38",
      "toolName": "Adobe Zoom Tool",
      "category": "Navigate 02",
      "tool_en": "Zoom Tool",
      "tool_ja": "ズーム",
      "extendscript": "app.selectTool('Adobe Zoom Tool');",
      "applescript": "Select Tool tool name \"Adobe Zoom Tool\"",
      "jxa": "app.selectTool({toolName: 'Adobe Zoom Tool'});",
      "minVersion": "24"
    },
    {
      "index": 39,
      "id": "toolName_39",
      "toolName": "Adobe Add Anchor Point Tool",
      "category": "Draw 01",
      "tool_en": "Add Anchor Point Tool",
      "tool_ja": "アンカーポイントの追加",
      "extendscript": "app.selectTool('Adobe Add Anchor Point Tool');",
      "applescript": "Select Tool tool name \"Adobe Add Anchor Point Tool\"",
      "jxa": "app.selectTool({toolName: 'Adobe Add Anchor Point Tool'});",
      "minVersion": "24"
    },
    {
      "index": 40,
      "id": "toolName_40",
      "toolName": "Adobe Delete Anchor Point Tool",
      "category": "Draw 01",
      "tool_en": "Delete Anchor Point Tool",
      "tool_ja": "アンカーポイントの削除",
      "extendscript": "app.selectTool('Adobe Delete Anchor Point Tool');",
      "applescript": "Select Tool tool name \"Adobe Delete Anchor Point Tool\"",
      "jxa": "app.selectTool({toolName: 'Adobe Delete Anchor Point Tool'});",
      "minVersion": "24"
    },
    {
      "index": 41,
      "id": "toolName_41",
      "toolName": "Adobe Anchor Point Tool",
      "category": "Draw 01",
      "tool_en": "Anchor Point Tool",
      "tool_ja": "アンカーポイント",
      "extendscript": "app.selectTool('Adobe Anchor Point Tool');",
      "applescript": "Select Tool tool name \"Adobe Anchor Point Tool\"",
      "jxa": "app.selectTool({toolName: 'Adobe Anchor Point Tool'});",
      "minVersion": "24"
    },
    {
      "index": 42,
      "id": "toolName_42",
      "toolName": "Adobe Gradient Vector Tool",
      "category": "Paint 01",
      "tool_en": "Gradient Tool",
      "tool_ja": "グラデーション",
      "extendscript": "app.selectTool('Adobe Gradient Vector Tool');",
      "applescript": "Select Tool tool name \"Adobe Gradient Vector Tool\"",
      "jxa": "app.selectTool({toolName: 'Adobe Gradient Vector Tool'});",
      "minVersion": "24"
    },
    {
      "index": 43,
      "id": "toolName_43",
      "toolName": "Adobe Brush Tool",
      "category": "Draw 05",
      "tool_en": "Paintbrush Tool",
      "tool_ja": "ブラシ",
      "extendscript": "app.selectTool('Adobe Brush Tool');",
      "applescript": "Select Tool tool name \"Adobe Brush Tool\"",
      "jxa": "app.selectTool({toolName: 'Adobe Brush Tool'});",
      "minVersion": "24"
    },
    {
      "index": 44,
      "id": "toolName_44",
      "toolName": "Adobe Eyedropper Tool",
      "category": "Modify 05",
      "tool_en": "Eyedropper Tool",
      "tool_ja": "スポイト",
      "extendscript": "app.selectTool('Adobe Eyedropper Tool');",
      "applescript": "Select Tool tool name \"Adobe Eyedropper Tool\"",
      "jxa": "app.selectTool({toolName: 'Adobe Eyedropper Tool'});",
      "minVersion": "24"
    },
    {
      "index": 45,
      "id": "toolName_45",
      "toolName": "Adobe Reshape Tool",
      "category": "Modify 02",
      "tool_en": "Reshape Tool",
      "tool_ja": "リシェイプ",
      "extendscript": "app.selectTool('Adobe Reshape Tool');",
      "applescript": "Select Tool tool name \"Adobe Reshape Tool\"",
      "jxa": "app.selectTool({toolName: 'Adobe Reshape Tool'});",
      "minVersion": "24"
    },
    {
      "index": 46,
      "id": "toolName_46",
      "toolName": "Adobe Width Tool",
      "category": "Modify 03",
      "tool_en": "Width Tool",
      "tool_ja": "線幅",
      "extendscript": "app.selectTool('Adobe Width Tool');",
      "applescript": "Select Tool tool name \"Adobe Width Tool\"",
      "jxa": "app.selectTool({toolName: 'Adobe Width Tool'});",
      "minVersion": "24"
    },
    {
      "index": 47,
      "id": "toolName_47",
      "toolName": "Adobe Knife Tool",
      "category": "Modify 07",
      "tool_en": "Knife",
      "tool_ja": "ナイフ",
      "extendscript": "app.selectTool('Adobe Knife Tool');",
      "applescript": "Select Tool tool name \"Adobe Knife Tool\"",
      "jxa": "app.selectTool({toolName: 'Adobe Knife Tool'});",
      "minVersion": "24"
    },
    {
      "index": 48,
      "id": "toolName_48",
      "toolName": "Adobe Shape Construction Regular Polygon Tool",
      "category": "Draw 04",
      "tool_en": "Polygon Tool",
      "tool_ja": "多角形",
      "extendscript": "app.selectTool('Adobe Shape Construction Regular Polygon Tool');",
      "applescript": "Select Tool tool name \"Adobe Shape Construction Regular Polygon Tool\"",
      "jxa": "app.selectTool({toolName: 'Adobe Shape Construction Regular Polygon Tool'});",
      "minVersion": "24"
    },
    {
      "index": 49,
      "id": "toolName_49",
      "toolName": "Adobe Shape Construction Star Tool",
      "category": "Draw 04",
      "tool_en": "Star Tool",
      "tool_ja": "スター",
      "extendscript": "app.selectTool('Adobe Shape Construction Star Tool');",
      "applescript": "Select Tool tool name \"Adobe Shape Construction Star Tool\"",
      "jxa": "app.selectTool({toolName: 'Adobe Shape Construction Star Tool'});",
      "minVersion": "24"
    },
    {
      "index": 50,
      "id": "toolName_50",
      "toolName": "Adobe Shape Construction Spiral Tool",
      "category": "Draw 03",
      "tool_en": "Spiral Tool",
      "tool_ja": "スパイラル",
      "extendscript": "app.selectTool('Adobe Shape Construction Spiral Tool');",
      "applescript": "Select Tool tool name \"Adobe Shape Construction Spiral Tool\"",
      "jxa": "app.selectTool({toolName: 'Adobe Shape Construction Spiral Tool'});",
      "minVersion": "24"
    },
    {
      "index": 51,
      "id": "toolName_51",
      "toolName": "Adobe Mesh Editing Tool",
      "category": "Paint 02",
      "tool_en": "Mesh Tool",
      "tool_ja": "メッシュ",
      "extendscript": "app.selectTool('Adobe Mesh Editing Tool');",
      "applescript": "Select Tool tool name \"Adobe Mesh Editing Tool\"",
      "jxa": "app.selectTool({toolName: 'Adobe Mesh Editing Tool'});",
      "minVersion": "24"
    },
    {
      "index": 52,
      "id": "toolName_52",
      "toolName": "Adobe Free Transform Tool",
      "category": "Modify 04",
      "tool_en": "Free Transform Tool",
      "tool_ja": "自由変形",
      "extendscript": "app.selectTool('Adobe Free Transform Tool');",
      "applescript": "Select Tool tool name \"Adobe Free Transform Tool\"",
      "jxa": "app.selectTool({toolName: 'Adobe Free Transform Tool'});",
      "minVersion": "24"
    },
    {
      "index": 53,
      "id": "toolName_53",
      "toolName": "Adobe Direct Lasso Tool",
      "category": "Select 04",
      "tool_en": "Lasso Tool",
      "tool_ja": "なげなわ",
      "extendscript": "app.selectTool('Adobe Direct Lasso Tool');",
      "applescript": "Select Tool tool name \"Adobe Direct Lasso Tool\"",
      "jxa": "app.selectTool({toolName: 'Adobe Direct Lasso Tool'});",
      "minVersion": "24"
    },
    {
      "index": 54,
      "id": "toolName_54",
      "toolName": "Adobe Ellipse Shape Tool",
      "category": "Draw 04",
      "tool_en": "Ellipse Tool",
      "tool_ja": "楕円形",
      "extendscript": "app.selectTool('Adobe Ellipse Shape Tool');",
      "applescript": "Select Tool tool name \"Adobe Ellipse Shape Tool\"",
      "jxa": "app.selectTool({toolName: 'Adobe Ellipse Shape Tool'});",
      "minVersion": "24"
    },
    {
      "index": 55,
      "id": "toolName_55",
      "toolName": "Adobe Rectangle Shape Tool",
      "category": "Draw 04",
      "tool_en": "Rectangle Tool",
      "tool_ja": "長方形",
      "extendscript": "app.selectTool('Adobe Rectangle Shape Tool');",
      "applescript": "Select Tool tool name \"Adobe Rectangle Shape Tool\"",
      "jxa": "app.selectTool({toolName: 'Adobe Rectangle Shape Tool'});",
      "minVersion": "24"
    },
    {
      "index": 56,
      "id": "toolName_56",
      "toolName": "Adobe Magic Wand Tool",
      "category": "Select 03",
      "tool_en": "Magic Wand Tool",
      "tool_ja": "自動選択",
      "extendscript": "app.selectTool('Adobe Magic Wand Tool');",
      "applescript": "Select Tool tool name \"Adobe Magic Wand Tool\"",
      "jxa": "app.selectTool({toolName: 'Adobe Magic Wand Tool'});",
      "minVersion": "24"
    },
    {
      "index": 57,
      "id": "toolName_57",
      "toolName": "Adobe Line Tool",
      "category": "Draw 03",
      "tool_en": "Line Segment Tool",
      "tool_ja": "直線",
      "extendscript": "app.selectTool('Adobe Line Tool');",
      "applescript": "Select Tool tool name \"Adobe Line Tool\"",
      "jxa": "app.selectTool({toolName: 'Adobe Line Tool'});",
      "minVersion": "24"
    },
    {
      "index": 58,
      "id": "toolName_58",
      "toolName": "Adobe Arc Tool",
      "category": "Draw 03",
      "tool_en": "Arc Tool",
      "tool_ja": "円弧",
      "extendscript": "app.selectTool('Adobe Arc Tool');",
      "applescript": "Select Tool tool name \"Adobe Arc Tool\"",
      "jxa": "app.selectTool({toolName: 'Adobe Arc Tool'});",
      "minVersion": "24"
    },
    {
      "index": 59,
      "id": "toolName_59",
      "toolName": "Adobe Rectangular Grid Tool",
      "category": "Draw 03",
      "tool_en": "Rectangular Grid Tool",
      "tool_ja": "長方形グリッド",
      "extendscript": "app.selectTool('Adobe Rectangular Grid Tool');",
      "applescript": "Select Tool tool name \"Adobe Rectangular Grid Tool\"",
      "jxa": "app.selectTool({toolName: 'Adobe Rectangular Grid Tool'});",
      "minVersion": "24"
    },
    {
      "index": 60,
      "id": "toolName_60",
      "toolName": "Adobe Polar Grid Tool",
      "category": "Draw 03",
      "tool_en": "Polar Grid Tool",
      "tool_ja": "同心円グリッド",
      "extendscript": "app.selectTool('Adobe Polar Grid Tool');",
      "applescript": "Select Tool tool name \"Adobe Polar Grid Tool\"",
      "jxa": "app.selectTool({toolName: 'Adobe Polar Grid Tool'});",
      "minVersion": "24"
    },
    {
      "index": 61,
      "id": "toolName_61",
      "toolName": "Adobe Flare Tool",
      "category": "Draw 04",
      "tool_en": "Flare Tool",
      "tool_ja": "フレア",
      "extendscript": "app.selectTool('Adobe Flare Tool');",
      "applescript": "Select Tool tool name \"Adobe Flare Tool\"",
      "jxa": "app.selectTool({toolName: 'Adobe Flare Tool'});",
      "minVersion": "24"
    },
    {
      "index": 62,
      "id": "toolName_62",
      "toolName": "Adobe Warp Tool",
      "category": "Modify 03",
      "tool_en": "Warp tool",
      "tool_ja": "ワープ",
      "extendscript": "app.selectTool('Adobe Warp Tool');",
      "applescript": "Select Tool tool name \"Adobe Warp Tool\"",
      "jxa": "app.selectTool({toolName: 'Adobe Warp Tool'});",
      "minVersion": "24"
    },
    {
      "index": 63,
      "id": "toolName_63",
      "toolName": "Adobe New Twirl Tool",
      "category": "Modify 03",
      "tool_en": "Twirl Tool",
      "tool_ja": "うねり",
      "extendscript": "app.selectTool('Adobe New Twirl Tool');",
      "applescript": "Select Tool tool name \"Adobe New Twirl Tool\"",
      "jxa": "app.selectTool({toolName: 'Adobe New Twirl Tool'});",
      "minVersion": "24"
    },
    {
      "index": 64,
      "id": "toolName_64",
      "toolName": "Adobe Pucker Tool",
      "category": "Modify 03",
      "tool_en": "Pucker Tool",
      "tool_ja": "収縮",
      "extendscript": "app.selectTool('Adobe Pucker Tool');",
      "applescript": "Select Tool tool name \"Adobe Pucker Tool\"",
      "jxa": "app.selectTool({toolName: 'Adobe Pucker Tool'});",
      "minVersion": "24"
    },
    {
      "index": 65,
      "id": "toolName_65",
      "toolName": "Adobe Bloat Tool",
      "category": "Modify 03",
      "tool_en": "Bloat Tool",
      "tool_ja": "膨張",
      "extendscript": "app.selectTool('Adobe Bloat Tool');",
      "applescript": "Select Tool tool name \"Adobe Bloat Tool\"",
      "jxa": "app.selectTool({toolName: 'Adobe Bloat Tool'});",
      "minVersion": "24"
    },
    {
      "index": 66,
      "id": "toolName_66",
      "toolName": "Adobe Scallop Tool",
      "category": "Modify 03",
      "tool_en": "Scallop Tool",
      "tool_ja": "ひだ",
      "extendscript": "app.selectTool('Adobe Scallop Tool');",
      "applescript": "Select Tool tool name \"Adobe Scallop Tool\"",
      "jxa": "app.selectTool({toolName: 'Adobe Scallop Tool'});",
      "minVersion": "24"
    },
    {
      "index": 67,
      "id": "toolName_67",
      "toolName": "Adobe Cyrstallize Tool",
      "category": "Modify 03",
      "tool_en": "Crystallize Tool",
      "tool_ja": "クラウン",
      "extendscript": "app.selectTool('Adobe Cyrstallize Tool');",
      "applescript": "Select Tool tool name \"Adobe Cyrstallize Tool\"",
      "jxa": "app.selectTool({toolName: 'Adobe Cyrstallize Tool'});",
      "minVersion": "24"
    },
    {
      "index": 68,
      "id": "toolName_68",
      "toolName": "Adobe Wrinkle Tool",
      "category": "Modify 03",
      "tool_en": "Wrinkle Tool",
      "tool_ja": "リンクル",
      "extendscript": "app.selectTool('Adobe Wrinkle Tool');",
      "applescript": "Select Tool tool name \"Adobe Wrinkle Tool\"",
      "jxa": "app.selectTool({toolName: 'Adobe Wrinkle Tool'});",
      "minVersion": "24"
    },
    {
      "index": 69,
      "id": "toolName_69",
      "toolName": "Adobe Slice Tool",
      "category": "Draw 09",
      "tool_en": "Slice Tool",
      "tool_ja": "スライス",
      "extendscript": "app.selectTool('Adobe Slice Tool');",
      "applescript": "Select Tool tool name \"Adobe Slice Tool\"",
      "jxa": "app.selectTool({toolName: 'Adobe Slice Tool'});",
      "minVersion": "24"
    },
    {
      "index": 70,
      "id": "toolName_70",
      "toolName": "Adobe Slice Select Tool",
      "category": "Draw 09",
      "tool_en": "Slice Selection Tool",
      "tool_ja": "スライス選択",
      "extendscript": "app.selectTool('Adobe Slice Select Tool');",
      "applescript": "Select Tool tool name \"Adobe Slice Select Tool\"",
      "jxa": "app.selectTool({toolName: 'Adobe Slice Select Tool'});",
      "minVersion": "24"
    },
    {
      "index": 71,
      "id": "toolName_71",
      "toolName": "Adobe Symbol Sprayer Tool",
      "category": "Draw 07",
      "tool_en": "Symbol Spayer Tool",
      "tool_ja": "シンボルスプレー",
      "extendscript": "app.selectTool('Adobe Symbol Sprayer Tool');",
      "applescript": "Select Tool tool name \"Adobe Symbol Sprayer Tool\"",
      "jxa": "app.selectTool({toolName: 'Adobe Symbol Sprayer Tool'});",
      "minVersion": "24"
    },
    {
      "index": 72,
      "id": "toolName_72",
      "toolName": "Adobe Symbol Shifter Tool",
      "category": "Draw 07",
      "tool_en": "Symbol Shifter Tool",
      "tool_ja": "シンボルシフト",
      "extendscript": "app.selectTool('Adobe Symbol Shifter Tool');",
      "applescript": "Select Tool tool name \"Adobe Symbol Shifter Tool\"",
      "jxa": "app.selectTool({toolName: 'Adobe Symbol Shifter Tool'});",
      "minVersion": "24"
    },
    {
      "index": 73,
      "id": "toolName_73",
      "toolName": "Adobe Symbol Scruncher Tool",
      "category": "Draw 07",
      "tool_en": "Symbol Scruncher Tool",
      "tool_ja": "シンボルスクランチ",
      "extendscript": "app.selectTool('Adobe Symbol Scruncher Tool');",
      "applescript": "Select Tool tool name \"Adobe Symbol Scruncher Tool\"",
      "jxa": "app.selectTool({toolName: 'Adobe Symbol Scruncher Tool'});",
      "minVersion": "24"
    },
    {
      "index": 74,
      "id": "toolName_74",
      "toolName": "Adobe Symbol Sizer Tool",
      "category": "Draw 07",
      "tool_en": "Symbol Sizer Tool",
      "tool_ja": "シンボルリサイズ",
      "extendscript": "app.selectTool('Adobe Symbol Sizer Tool');",
      "applescript": "Select Tool tool name \"Adobe Symbol Sizer Tool\"",
      "jxa": "app.selectTool({toolName: 'Adobe Symbol Sizer Tool'});",
      "minVersion": "24"
    },
    {
      "index": 75,
      "id": "toolName_75",
      "toolName": "Adobe Symbol Spinner Tool",
      "category": "Draw 07",
      "tool_en": "Symbol Spinner Tool",
      "tool_ja": "シンボルスピン",
      "extendscript": "app.selectTool('Adobe Symbol Spinner Tool');",
      "applescript": "Select Tool tool name \"Adobe Symbol Spinner Tool\"",
      "jxa": "app.selectTool({toolName: 'Adobe Symbol Spinner Tool'});",
      "minVersion": "24"
    },
    {
      "index": 76,
      "id": "toolName_76",
      "toolName": "Adobe Symbol Stainer Tool",
      "category": "Draw 07",
      "tool_en": "Symbol Stainer Tool",
      "tool_ja": "シンボルステイン",
      "extendscript": "app.selectTool('Adobe Symbol Stainer Tool');",
      "applescript": "Select Tool tool name \"Adobe Symbol Stainer Tool\"",
      "jxa": "app.selectTool({toolName: 'Adobe Symbol Stainer Tool'});",
      "minVersion": "24"
    },
    {
      "index": 77,
      "id": "toolName_77",
      "toolName": "Adobe Symbol Screener Tool",
      "category": "Draw 07",
      "tool_en": "Symbol Screener Tool",
      "tool_ja": "シンボルスクリーン",
      "extendscript": "app.selectTool('Adobe Symbol Screener Tool');",
      "applescript": "Select Tool tool name \"Adobe Symbol Screener Tool\"",
      "jxa": "app.selectTool({toolName: 'Adobe Symbol Screener Tool'});",
      "minVersion": "24"
    },
    {
      "index": 78,
      "id": "toolName_78",
      "toolName": "Adobe Symbol Styler Tool",
      "category": "Draw 07",
      "tool_en": "Symbol Styler Tool",
      "tool_ja": "シンボルスタイル",
      "extendscript": "app.selectTool('Adobe Symbol Styler Tool');",
      "applescript": "Select Tool tool name \"Adobe Symbol Styler Tool\"",
      "jxa": "app.selectTool({toolName: 'Adobe Symbol Styler Tool'});",
      "minVersion": "24"
    },
    {
      "index": 79,
      "id": "toolName_79",
      "toolName": "Adobe Planar Paintbucket Tool",
      "category": "Paint 03",
      "tool_en": "Live Paint Bucket",
      "tool_ja": "ライブペイント",
      "extendscript": "app.selectTool('Adobe Planar Paintbucket Tool');",
      "applescript": "Select Tool tool name \"Adobe Planar Paintbucket Tool\"",
      "jxa": "app.selectTool({toolName: 'Adobe Planar Paintbucket Tool'});",
      "minVersion": "24"
    },
    {
      "index": 80,
      "id": "toolName_80",
      "toolName": "Adobe Planar Face Select Tool",
      "category": "Paint 03",
      "tool_en": "Live Paint Selection Tool",
      "tool_ja": "ライブペイント選択",
      "extendscript": "app.selectTool('Adobe Planar Face Select Tool');",
      "applescript": "Select Tool tool name \"Adobe Planar Face Select Tool\"",
      "jxa": "app.selectTool({toolName: 'Adobe Planar Face Select Tool'});",
      "minVersion": "24"
    },
    {
      "index": 81,
      "id": "toolName_81",
      "toolName": "Adobe Eraser Tool",
      "category": "Modify 07",
      "tool_en": "Eraser Tool",
      "tool_ja": "消しゴム",
      "extendscript": "app.selectTool('Adobe Eraser Tool');",
      "applescript": "Select Tool tool name \"Adobe Eraser Tool\"",
      "jxa": "app.selectTool({toolName: 'Adobe Eraser Tool'});",
      "minVersion": "24"
    },
    {
      "index": 82,
      "id": "toolName_82",
      "toolName": "Adobe Crop Tool",
      "category": "Select 05",
      "tool_en": "Artboard Tool",
      "tool_ja": "アートボード",
      "extendscript": "app.selectTool('Adobe Crop Tool');",
      "applescript": "Select Tool tool name \"Adobe Crop Tool\"",
      "jxa": "app.selectTool({toolName: 'Adobe Crop Tool'});",
      "minVersion": "24"
    },
    {
      "index": 83,
      "id": "toolName_83",
      "toolName": "Adobe Blob Brush Tool",
      "category": "Draw 05",
      "tool_en": "Blob Tool",
      "tool_ja": "塗りブラシ",
      "extendscript": "app.selectTool('Adobe Blob Brush Tool');",
      "applescript": "Select Tool tool name \"Adobe Blob Brush Tool\"",
      "jxa": "app.selectTool({toolName: 'Adobe Blob Brush Tool'});",
      "minVersion": "24"
    },
    {
      "index": 84,
      "id": "toolName_84",
      "toolName": "Adobe Shape Builder Tool",
      "category": "Paint 03",
      "tool_en": "Shape Builder Tool",
      "tool_ja": "シェイプ形成",
      "extendscript": "app.selectTool('Adobe Shape Builder Tool');",
      "applescript": "Select Tool tool name \"Adobe Shape Builder Tool\"",
      "jxa": "app.selectTool({toolName: 'Adobe Shape Builder Tool'});",
      "minVersion": "24"
    },
    {
      "index": 85,
      "id": "toolName_85",
      "toolName": "Perspective Grid Tool",
      "category": "Draw 10",
      "tool_en": "Perspective Grid Tool",
      "tool_ja": "遠近グリッド",
      "extendscript": "app.selectTool('Perspective Grid Tool');",
      "applescript": "Select Tool tool name \"Perspective Grid Tool\"",
      "jxa": "app.selectTool({toolName: 'Perspective Grid Tool'});",
      "minVersion": "24"
    },
    {
      "index": 86,
      "id": "toolName_86",
      "toolName": "Perspective Selection Tool",
      "category": "Draw 10",
      "tool_en": "Perspective Selection Tool",
      "tool_ja": "遠近図形選択",
      "extendscript": "app.selectTool('Perspective Selection Tool');",
      "applescript": "Select Tool tool name \"Perspective Selection Tool\"",
      "jxa": "app.selectTool({toolName: 'Perspective Selection Tool'});",
      "minVersion": "24"
    },
    {
      "index": 87,
      "id": "toolName_87",
      "toolName": "Adobe Pattern Tile Tool",
      "category": "Unknown",
      "tool_en": "",
      "tool_ja": "",
      "extendscript": "app.selectTool('Adobe Pattern Tile Tool');",
      "applescript": "Select Tool tool name \"Adobe Pattern Tile Tool\"",
      "jxa": "app.selectTool({toolName: 'Adobe Pattern Tile Tool'});",
      "minVersion": "24"
    },
    {
      "index": 88,
      "id": "toolName_88",
      "toolName": "Adobe Place Gun Tool",
      "category": "Unknown",
      "tool_en": "",
      "tool_ja": "",
      "extendscript": "app.selectTool('Adobe Place Gun Tool');",
      "applescript": "Select Tool tool name \"Adobe Place Gun Tool\"",
      "jxa": "app.selectTool({toolName: 'Adobe Place Gun Tool'});",
      "minVersion": "24"
    },
    {
      "index": 89,
      "id": "toolName_89",
      "toolName": "Adobe Curvature Tool",
      "category": "Draw 02",
      "tool_en": "Curvature Tool",
      "tool_ja": "曲線ツール",
      "extendscript": "app.selectTool('Adobe Curvature Tool');",
      "applescript": "Select Tool tool name \"Adobe Curvature Tool\"",
      "jxa": "app.selectTool({toolName: 'Adobe Curvature Tool'});",
      "minVersion": "24"
    },
    {
      "index": 90,
      "id": "toolName_90",
      "toolName": "Adobe Shaper Tool",
      "category": "Draw 06",
      "tool_en": "Shaper Tool",
      "tool_ja": "Shaper ツール",
      "extendscript": "app.selectTool('Adobe Shaper Tool');",
      "applescript": "Select Tool tool name \"Adobe Shaper Tool\"",
      "jxa": "app.selectTool({toolName: 'Adobe Shaper Tool'});",
      "minVersion": "24"
    },
    {
      "index": 91,
      "id": "toolName_91",
      "toolName": "Adobe Symmetry Tool",
      "category": "Unknown",
      "tool_en": "",
      "tool_ja": "",
      "extendscript": "app.selectTool('Adobe Symmetry Tool');",
      "applescript": "Select Tool tool name \"Adobe Symmetry Tool\"",
      "jxa": "app.selectTool({toolName: 'Adobe Symmetry Tool'});",
      "minVersion": "24"
    },
    {
      "index": 92,
      "id": "toolName_92",
      "toolName": "Adobe Puppet Warp Tool",
      "category": "Modify 04",
      "tool_en": "Puppet Warp Tool",
      "tool_ja": "パペットワープツール",
      "extendscript": "app.selectTool('Adobe Puppet Warp Tool');",
      "applescript": "Select Tool tool name \"Adobe Puppet Warp Tool\"",
      "jxa": "app.selectTool({toolName: 'Adobe Puppet Warp Tool'});",
      "minVersion": "24"
    },
    {
      "index": 93,
      "id": "toolName_93",
      "toolName": "Adobe Diffusion Coloring Tool",
      "category": "Unknown",
      "tool_en": "",
      "tool_ja": "",
      "extendscript": "app.selectTool('Adobe Diffusion Coloring Tool');",
      "applescript": "Select Tool tool name \"Adobe Diffusion Coloring Tool\"",
      "jxa": "app.selectTool({toolName: 'Adobe Diffusion Coloring Tool'});",
      "minVersion": "24"
    },
    {
      "index": 94,
      "id": "toolName_94",
      "toolName": "Adobe Smart Edit Tool",
      "category": "Unknown",
      "tool_en": "",
      "tool_ja": "",
      "extendscript": "app.selectTool('Adobe Smart Edit Tool');",
      "applescript": "Select Tool tool name \"Adobe Smart Edit Tool\"",
      "jxa": "app.selectTool({toolName: 'Adobe Smart Edit Tool'});",
      "minVersion": "24"
    },
    {
      "index": 95,
      "id": "toolName_95",
      "toolName": "Adobe Color Theme Picker Tool",
      "category": "Unknown",
      "tool_en": "",
      "tool_ja": "カラーテーマピッカー",
      "extendscript": "app.selectTool('Adobe Color Theme Picker Tool');",
      "applescript": "Select Tool tool name \"Adobe Color Theme Picker Tool\"",
      "jxa": "app.selectTool({toolName: 'Adobe Color Theme Picker Tool'});",
      "minVersion": "24.3"
    },
    {
      "index": 96,
      "id": "toolName_96",
      "toolName": "Adobe Rotate Canvas Tool",
      "category": "Navigate 01",
      "tool_en": "Rotate View Tool",
      "tool_ja": "回転ビューツール",
      "extendscript": "app.selectTool('Adobe Rotate Canvas Tool');",
      "applescript": "Select Tool tool name \"Adobe Rotate Canvas Tool\"",
      "jxa": "app.selectTool({toolName: 'Adobe Rotate Canvas Tool'});",
      "minVersion": "25.3"
    },
    {
      "index": 97,
      "id": "toolName_97",
      "toolName": "Adobe Stencil Tool",
      "category": "Draw 06",
      "tool_en": "Stencil Tool",
      "tool_ja": "ステンシル",
      "extendscript": "app.selectTool('Adobe Stencil Tool');",
      "applescript": "Select Tool tool name \"Adobe Stencil Tool\"",
      "jxa": "app.selectTool({toolName: 'Adobe Stencil Tool'});",
      "minVersion": "24"
    },
    {
      "index": 98,
      "id": "toolName_98",
      "toolName": "Adobe Intertwine Zone Marker Tool",
      "category": "Modify 08",
      "tool_en": "",
      "tool_ja": "クロスと重なりを選択",
      "extendscript": "app.selectTool('Adobe Intertwine Zone Marker Tool');",
      "applescript": "Select Tool tool name \"Adobe Intertwine Zone Marker Tool\"",
      "jxa": "app.selectTool({toolName: 'Adobe Intertwine Zone Marker Tool'});",
      "minVersion": "27"
    },
    {
      "index": 99,
      "id": "toolName_99",
      "toolName": "Adobe Dimension Tool",
      "category": "Add Ons",
      "tool_en": "Dimension Tool",
      "tool_ja": "寸法ツール",
      "extendscript": "app.selectTool('Adobe Dimension Tool');",
      "applescript": "Select Tool tool name \"Adobe Dimension Tool\"",
      "jxa": "app.selectTool({toolName: 'Adobe Dimension Tool'});",
      "minVersion": "28.1"
    },
    {
      "index": 100,
      "id": "toolName_100",
      "toolName": "Adobe Constraints Tool",
      "category": "Modify 09",
      "tool_en": "Objects on Path",
      "tool_ja": "パス上オブジェクト",
      "extendscript": "app.selectTool('Adobe Constraints Tool');",
      "applescript": "Select Tool tool name \"Adobe Constraints Tool\"",
      "jxa": "app.selectTool({toolName: 'Adobe Constraints Tool'});",
      "minVersion": "29"
    }
  ]
}
